abersetz/__about__.py
abersetz/__init__.py
abersetz/__main__.py
abersetz/abersetz.py
abersetz/chunking.py
abersetz/cli.py
abersetz/cli_fast.py
abersetz/config.py
abersetz/engine_catalog.py
abersetz/engines.py
abersetz/openai_lite.py
abersetz/pipeline.py
abersetz/setup.py
abersetz/validation.py
abersetz-1.0.22.dist-info/METADATA
abersetz-1.0.22.dist-info/WHEEL
abersetz-1.0.22.dist-info/entry_points.txt
abersetz-1.0.22.dist-info/licenses/LICENSE
abersetz-1.0.22.dist-info/RECORD
