Metadata-Version: 2.4
Name: abersetz
Version: 1.0.22
Project-URL: Documentation, https://github.com/twardoch/abersetz#readme
Project-URL: Issues, https://github.com/twardoch/abersetz/issues
Project-URL: Source, https://github.com/twardoch/abersetz
Author-email: Adam Twardoch <adam+github@twardoch.com>
License: MIT
License-File: LICENSE
Requires-Python: >=3.10
Requires-Dist: deep-translator>=1.11
Requires-Dist: fire>=0.5
Requires-Dist: httpx>=0.25
Requires-Dist: langcodes>=3.4
Requires-Dist: language-data>=1.4.0
Requires-Dist: loguru>=0.7
Requires-Dist: platformdirs>=4.3
Requires-Dist: rich>=13.9
Requires-Dist: semantic-text-splitter>=0.7
Requires-Dist: tenacity>=8.4
Requires-Dist: tomli-w>=1.0
Requires-Dist: tomli>=2.0; python_version < '3.11'
Requires-Dist: translators>=5.9
